text_encrypt_decrypt/text_encrypt_decrypt.py
text_encrypt_decrypt-0.0.1.dist-info/LICENSE
text_encrypt_decrypt-0.0.1.dist-info/METADATA
text_encrypt_decrypt-0.0.1.dist-info/WHEEL
text_encrypt_decrypt-0.0.1.dist-info/top_level.txt
text_encrypt_decrypt-0.0.1.dist-info/RECORD
