Metadata-Version: 2.1
Name: text-encrypt-decrypt
Version: 0.0.1
Summary: plain text encryption and decryption with SHA256 algorithm.
Home-page: https://github.com/sujitmandal/text-encrypt-decrypt
Author: Sujit Mandal
Author-email: mandals974@gmail.com
License: MIT
Classifier: License :: OSI Approved :: MIT License
Classifier: Programming Language :: Python :: 2.7
Classifier: Programming Language :: Python :: 3.0
Classifier: Programming Language :: Python :: 3.5
Classifier: Programming Language :: Python :: 3.6
Classifier: Programming Language :: Python :: 3.7
Classifier: Programming Language :: Python :: 3.8
Classifier: Programming Language :: Python :: 3.9
Classifier: Programming Language :: Python :: 3.10
License-File: LICENSE
Requires-Dist: cryptography
